littlepaimon_utils/__init__.py
littlepaimon_utils/aiorequests.py
littlepaimon_utils/files.py
littlepaimon_utils/tools.py
littlepaimon_utils-1.0.1.dist-info/WHEEL
littlepaimon_utils-1.0.1.dist-info/METADATA
littlepaimon_utils-1.0.1.dist-info/RECORD
